batchfile/__init__.py
batchfile/__main__.py
batchfile/_functions.py
batchfile/batchfile.py
batchfile/replay.py
batchfile/textfile.py
batchfile.py-0.5.dist-info/LICENSE
batchfile.py-0.5.dist-info/METADATA
batchfile.py-0.5.dist-info/WHEEL
batchfile.py-0.5.dist-info/top_level.txt
batchfile.py-0.5.dist-info/RECORD
