Metadata-Version: 2.1
Name: batchfile.py
Version: 0.5
Summary: Run Windows batch files (.bat) using Python
Home-page: https://github.com/tassaron2/batchfile.py
Author: tassaron
License: MIT
Keywords: batchfile batch
Platform: UNKNOWN
Classifier: Development Status :: 3 - Alpha
Classifier: Intended Audience :: Developers
Classifier: Topic :: Software Development :: Interpreters
Classifier: Topic :: Terminals
Classifier: Topic :: System :: Shells
Classifier: Topic :: Games/Entertainment
Classifier: License :: OSI Approved :: MIT License
Classifier: Programming Language :: Python :: 3.6
